astrolog/__init__.py
astrolog/celestials.py
astrolog/coords.py
astrolog/natal.py
astrolog/primitives.py
astrolog/zodiac.py
astrolog-0.7.0.dist-info/METADATA
astrolog-0.7.0.dist-info/WHEEL
astrolog-0.7.0.dist-info/RECORD
